ucan/__init__.py
ucan/constants.py
ucan/core/__init__.py
ucan/core/attenuation.py
ucan/core/capability.py
ucan/core/plugins.py
ucan/core/semver.py
ucan/core/token.py
ucan/core/types.py
ucan/core/verify.py
ucan/default_plugins/__init__.py
ucan/default_plugins/ed25519.py
ucan/encoding.py
ucan/py.typed
ucan/schemas.py
ucan/utils.py
py_ucan-1.0.0.dist-info/LICENSE
py_ucan-1.0.0.dist-info/METADATA
py_ucan-1.0.0.dist-info/WHEEL
py_ucan-1.0.0.dist-info/RECORD
