Metadata-Version: 2.1
Name: py-ucan
Version: 1.0.0
Summary: Python Ucan
Home-page: https://github.com/fileverse/py-ucan
Author: Subham Agarwal
Author-email: 177206897+subham1099@users.noreply.github.com
Requires-Python: >=3.10,<4.0
Classifier: Programming Language :: Python
Classifier: Programming Language :: Python :: 3
Classifier: Programming Language :: Python :: 3.10
Classifier: Programming Language :: Python :: 3.11
Classifier: Programming Language :: Python :: 3.12
Requires-Dist: base58 (>=2.1.1,<3.0.0)
Requires-Dist: cryptography (>=43.0.0,<44.0.0)
Requires-Dist: poetry (>=1.8.3,<2.0.0)
Requires-Dist: pydantic (>=2.8.2,<3.0.0)
Requires-Dist: pyjwt (>=2.9.0,<3.0.0)
Requires-Dist: typing-extensions (>=4.12.2,<5.0.0)
Project-URL: Bug Tracker, https://github.com/fileverse/py-ucan/issues
Project-URL: Documentation, https://github.com/fileverse/py-ucan
Project-URL: Repository, https://github.com/fileverse/py-ucan
